MANIFEST.in
README.md
README.rst
__main__.py
requirements.txt
setup.py
common/__init__.py
common/action/__init__.py
common/action/action_event.py
common/action/assert_event.py
common/action/browser_event.py
common/action/element_event.py
common/action/http_apply.py
common/action/table_event.py
config/__init__.py
config/config.ini
config/email.ini
config/file.ini
config/read_ini.py
image/2018-07-27/el20180727145548.png
lib/HTMLTestRunner.py
lib/__init__.py
lib/__pycache__/HTMLTestRunner.cpython-36.pyc
lib/__pycache__/__init__.cpython-36.pyc
lib/driver/IEDriverServer3_11_0.exe
lib/driver/chromedriver.exe
lib/driver/chromedriver2_29.exe
lib/driver/chromedriver2_37.exe
lib/driver/geckodriver0_18_0.exe
lib/driver/geckodriver0_20_1.exe
lib/driver/readme.txt
lib/jar/Test.jar
lib/jar/Test2.jar
lib/jar/Test3.jar
lib/jar/hbase-event.jar
lib/jar/log4j.properties
logs/201804171641.log
logs/201804171643.log
logs/201804171700.log
pulid/__init__.py
pulid/bulid.py
pulid/cmdline.py
report/report.html
src/__init__.py
src/framework/__init__.py
src/framework/custom_exception.py
src/framework/fail_reload.py
src/framework/relation_case.py
src/framework/run_case.py
src/framework/test_runner.py
src/framework/web_element.py
src/util/__init__.py
src/util/browser_util.py
src/util/get_root_path.py
src/util/global_util.py
src/util/hbase_util.py
src/util/http.py
src/util/jar_util.py
src/util/linux_util.py
src/util/logger_util.py
src/util/readfile_util.py
src/util/sendemail_util.py
src/util/sql_util.py
src/util/upload_file.py
suite/__init__.py
suite/data/testData.xlsx
suite/test/__init__.py
suite/test/case/逾期流程测试.xlsx
suite/test/case/逾期流程测试module.xlsx
suite/test/module/关闭浏览器.xlsx
suite/test/module/打开浏览器.xlsx
suite/test/module/搜索.xlsx
suite/test/module/登录.xlsx
suite/test/pageobj/逾期流程测试控件.yaml
suite/test/realize/__init__.py
suite/test/realize/close_browser.py
suite/test/realize/login.py
suite/test/realize/open_browser.py
suite/test/realize/search.py