Metadata-Version: 1.2
Name: dafeiauto
Version: 2.0.11
Summary: python 自动化测试
Home-page: http://gitlab.dafytech.com/gitlab/aotutest.git
Author: DAFYAUTOTEST
Author-email: xieyongyuan@dafy.com
Maintainer: xieyongyuan
Maintainer-email: xieyongyuan@dafy.com
License: BSD License
Platform: all
Classifier: Development Status :: 4 - Beta
Classifier: Operating System :: OS Independent
Classifier: Intended Audience :: Developers
Classifier: License :: OSI Approved :: BSD License
Classifier: Programming Language :: Python
Classifier: Programming Language :: Python :: Implementation
Classifier: Programming Language :: Python :: 3
Classifier: Programming Language :: Python :: 3.4
Classifier: Programming Language :: Python :: 3.5
Classifier: Programming Language :: Python :: 3.6
Classifier: Topic :: Software Development :: Libraries
